datajuicer/__init__.py
datajuicer/architecture.py
datajuicer/database.py
datajuicer/datajuicer.py
datajuicer/in_out.py
datajuicer/parser.py
datajuicer/utils.py
datajuicer-0.0.3.dist-info/LICENSE
datajuicer-0.0.3.dist-info/METADATA
datajuicer-0.0.3.dist-info/WHEEL
datajuicer-0.0.3.dist-info/top_level.txt
datajuicer-0.0.3.dist-info/RECORD
